AUTHORS
CHANGELOG.txt
DESCRIPTION
LICENSE
MANIFEST.in
README.rst
setup.py
django_flipbook.egg-info/PKG-INFO
django_flipbook.egg-info/SOURCES.txt
django_flipbook.egg-info/dependency_links.txt
django_flipbook.egg-info/requires.txt
django_flipbook.egg-info/top_level.txt
flipbook/__init__.py
flipbook/admin.py
flipbook/models.py
flipbook/urls.py
flipbook/views.py
flipbook/migrations/0001_initial.py
flipbook/migrations/0002_auto__add_flipbookcategory.py
flipbook/migrations/0003_auto__add_field_flipbook_category.py
flipbook/migrations/0004_auto__add_flipbookpage.py
flipbook/migrations/0005_auto__del_field_flipbook_folder.py
flipbook/migrations/0006_auto__add_field_flipbookpage_image.py
flipbook/migrations/0007_auto__add_field_flipbookpage_page_type.py
flipbook/migrations/0008_auto__add_field_flipbook_book_type.py
flipbook/migrations/0009_auto__add_field_flipbook_image__add_unique_flipbook_slug__add_unique_f.py
flipbook/migrations/0010_auto__add_field_flipbook_url__add_field_flipbook_email.py
flipbook/migrations/__init__.py
flipbook/static/flipbook/css/bookblock.css
flipbook/static/flipbook/fonts/.DS_Store
flipbook/static/flipbook/fonts/arrows/arrows.dev.svg
flipbook/static/flipbook/fonts/arrows/arrows.eot
flipbook/static/flipbook/fonts/arrows/arrows.svg
flipbook/static/flipbook/fonts/arrows/arrows.ttf
flipbook/static/flipbook/fonts/arrows/arrows.woff
flipbook/static/flipbook/fonts/arrows/license.txt
flipbook/static/flipbook/fonts/codropsicons/.DS_Store
flipbook/static/flipbook/fonts/codropsicons/codropsicons.eot
flipbook/static/flipbook/fonts/codropsicons/codropsicons.svg
flipbook/static/flipbook/fonts/codropsicons/codropsicons.ttf
flipbook/static/flipbook/fonts/codropsicons/codropsicons.woff
flipbook/static/flipbook/fonts/codropsicons/license.txt
flipbook/static/flipbook/js/jquery.bookblock.js
flipbook/static/flipbook/js/jquerypp.custom.js
flipbook/static/flipbook/js/modernizr.custom.js
flipbook/templates/flipbook/flipbook_detail.html
flipbook/templates/flipbook/flipbook_list.html
flipbook/templates/flipbook/flipbookcategory_detail.html
flipbook/tests/__init__.py
flipbook/tests/factories.py
flipbook/tests/models_tests.py
flipbook/tests/runtests.py
