Metadata-Version: 1.0
Name: django-flipbook
Version: 0.3.6
Summary: A reusable Django app that displays an image gallery as a flipbook.
Home-page: https://github.com/bitmazk/django-flipbook
Author: Tobias Lorenz
Author-email: tobias.lorenz@bitmazk.com
License: The MIT License
Keywords: django,app,reusable,flipbook,gallery,ebook
Platform: OS Independent
